{
  "metadata": {
    "video_id": "submissions_f21ac459-7925-4a45-ab8d-9067a8667382_E",
    "sign": "valid",
    "resolution": [
      480,
      360
    ],
    "fps": 30.0,
    "frame_count": 104,
    "codec": 875967080,
    "mediapipe_version": "0.10.21",
    "rotation_applied": 90
  },
  "normalisation": {
    "method": "pchip_uniform_nan_robust",
    "frame_num": 10,
    "source_total_frames": 104,
    "compression_ratio": 10.4
  },
  "frames": [
    {
      "frame_index": 0,
      "timestamp": 0.0,
      "hands": {
        "left": [
          {
            "landmark_id": 0,
            "x": -0.32848034,
            "y": 0.83852172
          },
          {
            "landmark_id": 1,
            "x": -0.23356215,
            "y": 0.82649386
          },
          {
            "landmark_id": 2,
            "x": -0.16172606,
            "y": 0.80523455
          },
          {
            "landmark_id": 3,
            "x": -0.12066377,
            "y": 0.78617722
          },
          {
            "landmark_id": 4,
            "x": -0.08801088,
            "y": 0.76200849
          },
          {
            "landmark_id": 5,
            "x": -0.23874346,
            "y": 0.7515294
          },
          {
            "landmark_id": 6,
            "x": -0.21192077,
            "y": 0.7777003
          },
          {
            "landmark_id": 7,
            "x": -0.19113544,
            "y": 0.82783443
          },
          {
            "landmark_id": 8,
            "x": -0.17927281,
            "y": 0.87257814
          },
          {
            "landmark_id": 9,
            "x": -0.31248576,
            "y": 0.76785767
          },
          {
            "landmark_id": 10,
            "x": -0.28334743,
            "y": 0.81166166
          },
          {
            "landmark_id": 11,
            "x": -0.255812,
            "y": 0.86897886
          },
          {
            "landmark_id": 12,
            "x": -0.23845417,
            "y": 0.91589457
          },
          {
            "landmark_id": 13,
            "x": -0.37157366,
            "y": 0.79625463
          },
          {
            "landmark_id": 14,
            "x": -0.35062022,
            "y": 0.83471876
          },
          {
            "landmark_id": 15,
            "x": -0.32094038,
            "y": 0.88526255
          },
          {
            "landmark_id": 16,
            "x": -0.30076743,
            "y": 0.92496872
          },
          {
            "landmark_id": 17,
            "x": -0.41479132,
            "y": 0.82952559
          },
          {
            "landmark_id": 18,
            "x": -0.41482445,
            "y": 0.86393285
          },
          {
            "landmark_id": 19,
            "x": -0.39317738,
            "y": 0.89971614
          },
          {
            "landmark_id": 20,
            "x": -0.37377623,
            "y": 0.92706734
          }
        ],
        "right": [
          {
            "landmark_id": 0,
            "x": 0.75594276,
            "y": 0.93956447
          },
          {
            "landmark_id": 1,
            "x": 0.69226354,
            "y": 0.90904188
          },
          {
            "landmark_id": 2,
            "x": 0.63026905,
            "y": 0.90651035
          },
          {
            "landmark_id": 3,
            "x": 0.57296157,
            "y": 0.9210943
          },
          {
            "landmark_id": 4,
            "x": 0.52980757,
            "y": 0.93860489
          },
          {
            "landmark_id": 5,
            "x": 0.63933331,
            "y": 0.95072746
          },
          {
            "landmark_id": 6,
            "x": 0.55711573,
            "y": 0.9799118
          },
          {
            "landmark_id": 7,
            "x": 0.52510947,
            "y": 0.98206478
          },
          {
            "landmark_id": 8,
            "x": 0.52366412,
            "y": 0.97277945
          },
          {
            "landmark_id": 9,
            "x": 0.66174281,
            "y": 0.98444939
          },
          {
            "landmark_id": 10,
            "x": 0.58080029,
            "y": 1.01066494
          },
          {
            "landmark_id": 11,
            "x": 0.56029868,
            "y": 1.00750887
          },
          {
            "landmark_id": 12,
            "x": 0.56406325,
            "y": 0.99858445
          },
          {
            "landmark_id": 13,
            "x": 0.68452871,
            "y": 1.00826681
          },
          {
            "landmark_id": 14,
            "x": 0.61634463,
            "y": 1.03270912
          },
          {
            "landmark_id": 15,
            "x": 0.59895277,
            "y": 1.02842891
          },
          {
            "landmark_id": 16,
            "x": 0.60367835,
            "y": 1.01833344
          },
          {
            "landmark_id": 17,
            "x": 0.70383596,
            "y": 1.02402246
          },
          {
            "landmark_id": 18,
            "x": 0.65517926,
            "y": 1.04433286
          },
          {
            "landmark_id": 19,
            "x": 0.638542,
            "y": 1.04184115
          },
          {
            "landmark_id": 20,
            "x": 0.63867545,
            "y": 1.03514767
          }
        ]
      }
    },
    {
      "frame_index": 1,
      "timestamp": 0.11111111,
      "hands": {
        "left": [
          {
            "landmark_id": 0,
            "x": 0.24724736,
            "y": 0.83852172
          },
          {
            "landmark_id": 1,
            "x": 0.34414528,
            "y": 0.82649386
          },
          {
            "landmark_id": 2,
            "x": 0.41598313,
            "y": 0.80523455
          },
          {
            "landmark_id": 3,
            "x": 0.45704542,
            "y": 0.78617722
          },
          {
            "landmark_id": 4,
            "x": 0.48969831,
            "y": 0.76200849
          },
          {
            "landmark_id": 5,
            "x": 0.33896573,
            "y": 0.7515294
          },
          {
            "landmark_id": 6,
            "x": 0.36578842,
            "y": 0.7777003
          },
          {
            "landmark_id": 7,
            "x": 0.38657375,
            "y": 0.82783443
          },
          {
            "landmark_id": 8,
            "x": 0.39456217,
            "y": 0.87257814
          },
          {
            "landmark_id": 9,
            "x": 0.26334976,
            "y": 0.76785767
          },
          {
            "landmark_id": 10,
            "x": 0.29436176,
            "y": 0.81166166
          },
          {
            "landmark_id": 11,
            "x": 0.32179983,
            "y": 0.86897886
          },
          {
            "landmark_id": 12,
            "x": 0.3348076,
            "y": 0.91589457
          },
          {
            "landmark_id": 13,
            "x": 0.20257486,
            "y": 0.79625463
          },
          {
            "landmark_id": 14,
            "x": 0.22708897,
            "y": 0.83471876
          },
          {
            "landmark_id": 15,
            "x": 0.25676881,
            "y": 0.88526255
          },
          {
            "landmark_id": 16,
            "x": 0.27613531,
            "y": 0.92496872
          },
          {
            "landmark_id": 17,
            "x": 0.15918364,
            "y": 0.82952559
          },
          {
            "landmark_id": 18,
            "x": 0.16288474,
            "y": 0.86393285
          },
          {
            "landmark_id": 19,
            "x": 0.18453181,
            "y": 0.89971614
          },
          {
            "landmark_id": 20,
            "x": 0.20393296,
            "y": 0.92706734
          }
        ],
        "right": [
          {
            "landmark_id": 0,
            "x": 0.74602744,
            "y": 0.93073631
          },
          {
            "landmark_id": 1,
            "x": 0.68308512,
            "y": 0.90126332
          },
          {
            "landmark_id": 2,
            "x": 0.61847716,
            "y": 0.89870008
          },
          {
            "landmark_id": 3,
            "x": 0.56029116,
            "y": 0.91552659
          },
          {
            "landmark_id": 4,
            "x": 0.51821991,
            "y": 0.93510133
          },
          {
            "landmark_id": 5,
            "x": 0.6217658,
            "y": 0.93772589
          },
          {
            "landmark_id": 6,
            "x": 0.5365443,
            "y": 0.97237626
          },
          {
            "landmark_id": 7,
            "x": 0.50955498,
            "y": 0.9774637
          },
          {
            "landmark_id": 8,
            "x": 0.51403651,
            "y": 0.97001402
          },
          {
            "landmark_id": 9,
            "x": 0.64411552,
            "y": 0.97303678
          },
          {
            "landmark_id": 10,
            "x": 0.56142371,
            "y": 1.00439389
          },
          {
            "landmark_id": 11,
            "x": 0.54782248,
            "y": 1.00276775
          },
          {
            "landmark_id": 12,
            "x": 0.55730953,
            "y": 0.99541011
          },
          {
            "landmark_id": 13,
            "x": 0.66874431,
            "y": 1.00049966
          },
          {
            "landmark_id": 14,
            "x": 0.59776965,
            "y": 1.02937773
          },
          {
            "landmark_id": 15,
            "x": 0.58657442,
            "y": 1.02547476
          },
          {
            "landmark_id": 16,
            "x": 0.59640867,
            "y": 1.01590363
          },
          {
            "landmark_id": 17,
            "x": 0.69076208,
            "y": 1.0209423
          },
          {
            "landmark_id": 18,
            "x": 0.63756121,
            "y": 1.04434681
          },
          {
            "landmark_id": 19,
            "x": 0.62655,
            "y": 1.04096608
          },
          {
            "landmark_id": 20,
            "x": 0.63223306,
            "y": 1.03401524
          }
        ]
      }
    },
    {
      "frame_index": 2,
      "timestamp": 0.22222222,
      "hands": {
        "left": [
          {
            "landmark_id": 0,
            "x": 0.29233291,
            "y": 0.60301333
          },
          {
            "landmark_id": 1,
            "x": 0.35388727,
            "y": 0.59180328
          },
          {
            "landmark_id": 2,
            "x": 0.40371009,
            "y": 0.56585068
          },
          {
            "landmark_id": 3,
            "x": 0.44040382,
            "y": 0.54665141
          },
          {
            "landmark_id": 4,
            "x": 0.47392541,
            "y": 0.53406321
          },
          {
            "landmark_id": 5,
            "x": 0.37545164,
            "y": 0.51175393
          },
          {
            "landmark_id": 6,
            "x": 0.40416327,
            "y": 0.47207941
          },
          {
            "landmark_id": 7,
            "x": 0.42208615,
            "y": 0.44727888
          },
          {
            "landmark_id": 8,
            "x": 0.43800315,
            "y": 0.42546548
          },
          {
            "landmark_id": 9,
            "x": 0.33932918,
            "y": 0.50247108
          },
          {
            "landmark_id": 10,
            "x": 0.36569078,
            "y": 0.45591757
          },
          {
            "landmark_id": 11,
            "x": 0.38544561,
            "y": 0.42697549
          },
          {
            "landmark_id": 12,
            "x": 0.40255502,
            "y": 0.40179687
          },
          {
            "landmark_id": 13,
            "x": 0.29978831,
            "y": 0.50401431
          },
          {
            "landmark_id": 14,
            "x": 0.31258097,
            "y": 0.45687431
          },
          {
            "landmark_id": 15,
            "x": 0.32488081,
            "y": 0.42785932
          },
          {
            "landmark_id": 16,
            "x": 0.3396175,
            "y": 0.40263335
          },
          {
            "landmark_id": 17,
            "x": 0.25859333,
            "y": 0.51393688
          },
          {
            "landmark_id": 18,
            "x": 0.25558992,
            "y": 0.47795083
          },
          {
            "landmark_id": 19,
            "x": 0.25882792,
            "y": 0.4553967
          },
          {
            "landmark_id": 20,
            "x": 0.26754093,
            "y": 0.43456845
          }
        ],
        "right": [
          {
            "landmark_id": 0,
            "x": 0.72324303,
            "y": 0.91646559
          },
          {
            "landmark_id": 1,
            "x": 0.66212041,
            "y": 0.89129624
          },
          {
            "landmark_id": 2,
            "x": 0.5977092,
            "y": 0.89342555
          },
          {
            "landmark_id": 3,
            "x": 0.54468201,
            "y": 0.90903772
          },
          {
            "landmark_id": 4,
            "x": 0.50547611,
            "y": 0.92528999
          },
          {
            "landmark_id": 5,
            "x": 0.59416657,
            "y": 0.92913847
          },
          {
            "landmark_id": 6,
            "x": 0.52321016,
            "y": 0.95963164
          },
          {
            "landmark_id": 7,
            "x": 0.48950476,
            "y": 0.97815908
          },
          {
            "landmark_id": 8,
            "x": 0.47485602,
            "y": 0.98991444
          },
          {
            "landmark_id": 9,
            "x": 0.6196951,
            "y": 0.96054624
          },
          {
            "landmark_id": 10,
            "x": 0.55105616,
            "y": 0.9918109
          },
          {
            "landmark_id": 11,
            "x": 0.52239678,
            "y": 1.0065041
          },
          {
            "landmark_id": 12,
            "x": 0.5128782,
            "y": 1.01442739
          },
          {
            "landmark_id": 13,
            "x": 0.64993585,
            "y": 0.98617449
          },
          {
            "landmark_id": 14,
            "x": 0.5913956,
            "y": 1.01810492
          },
          {
            "landmark_id": 15,
            "x": 0.56582188,
            "y": 1.03097159
          },
          {
            "landmark_id": 16,
            "x": 0.55602394,
            "y": 1.03637957
          },
          {
            "landmark_id": 17,
            "x": 0.68124581,
            "y": 1.00539418
          },
          {
            "landmark_id": 18,
            "x": 0.64076684,
            "y": 1.0343216
          },
          {
            "landmark_id": 19,
            "x": 0.61952186,
            "y": 1.04633823
          },
          {
            "landmark_id": 20,
            "x": 0.60746701,
            "y": 1.05329605
          }
        ]
      }
    },
    {
      "frame_index": 3,
      "timestamp": 0.33333333,
      "hands": {
        "left": [
          {
            "landmark_id": 0,
            "x": 0.2973825,
            "y": 0.572733
          },
          {
            "landmark_id": 1,
            "x": 0.35764804,
            "y": 0.5618294
          },
          {
            "landmark_id": 2,
            "x": 0.40512935,
            "y": 0.53779794
          },
          {
            "landmark_id": 3,
            "x": 0.44029959,
            "y": 0.51958366
          },
          {
            "landmark_id": 4,
            "x": 0.47423244,
            "y": 0.50989288
          },
          {
            "landmark_id": 5,
            "x": 0.37888521,
            "y": 0.48456328
          },
          {
            "landmark_id": 6,
            "x": 0.40673828,
            "y": 0.44603139
          },
          {
            "landmark_id": 7,
            "x": 0.42453423,
            "y": 0.42250244
          },
          {
            "landmark_id": 8,
            "x": 0.43974742,
            "y": 0.40183999
          },
          {
            "landmark_id": 9,
            "x": 0.34425194,
            "y": 0.47527321
          },
          {
            "landmark_id": 10,
            "x": 0.37012552,
            "y": 0.43015798
          },
          {
            "landmark_id": 11,
            "x": 0.38890475,
            "y": 0.40275887
          },
          {
            "landmark_id": 12,
            "x": 0.40459872,
            "y": 0.37919062
          },
          {
            "landmark_id": 13,
            "x": 0.30639431,
            "y": 0.47589034
          },
          {
            "landmark_id": 14,
            "x": 0.31976508,
            "y": 0.42988763
          },
          {
            "landmark_id": 15,
            "x": 0.33246849,
            "y": 0.40131329
          },
          {
            "landmark_id": 16,
            "x": 0.34641411,
            "y": 0.37683716
          },
          {
            "landmark_id": 17,
            "x": 0.26598569,
            "y": 0.48381264
          },
          {
            "landmark_id": 18,
            "x": 0.26423209,
            "y": 0.44809973
          },
          {
            "landmark_id": 19,
            "x": 0.26753721,
            "y": 0.42466733
          },
          {
            "landmark_id": 20,
            "x": 0.27508169,
            "y": 0.40257025
          }
        ],
        "right": [
          {
            "landmark_id": 0,
            "x": 0.76361687,
            "y": 0.79633544
          },
          {
            "landmark_id": 1,
            "x": 0.71674619,
            "y": 0.76766879
          },
          {
            "landmark_id": 2,
            "x": 0.63518951,
            "y": 0.75189207
          },
          {
            "landmark_id": 3,
            "x": 0.56942762,
            "y": 0.75147671
          },
          {
            "landmark_id": 4,
            "x": 0.52318237,
            "y": 0.75477512
          },
          {
            "landmark_id": 5,
            "x": 0.656436,
            "y": 0.74244723
          },
          {
            "landmark_id": 6,
            "x": 0.5795592,
            "y": 0.74470431
          },
          {
            "landmark_id": 7,
            "x": 0.53042918,
            "y": 0.75374815
          },
          {
            "landmark_id": 8,
            "x": 0.49771928,
            "y": 0.76286293
          },
          {
            "landmark_id": 9,
            "x": 0.67370122,
            "y": 0.76919834
          },
          {
            "landmark_id": 10,
            "x": 0.57343723,
            "y": 0.79227866
          },
          {
            "landmark_id": 11,
            "x": 0.55887024,
            "y": 0.80571592
          },
          {
            "landmark_id": 12,
            "x": 0.57122217,
            "y": 0.8132236
          },
          {
            "landmark_id": 13,
            "x": 0.69430949,
            "y": 0.80269806
          },
          {
            "landmark_id": 14,
            "x": 0.59470738,
            "y": 0.83141499
          },
          {
            "landmark_id": 15,
            "x": 0.61052405,
            "y": 0.83425717
          },
          {
            "landmark_id": 16,
            "x": 0.64459638,
            "y": 0.82823768
          },
          {
            "landmark_id": 17,
            "x": 0.71563955,
            "y": 0.84096181
          },
          {
            "landmark_id": 18,
            "x": 0.63844267,
            "y": 0.86386085
          },
          {
            "landmark_id": 19,
            "x": 0.65389156,
            "y": 0.86139933
          },
          {
            "landmark_id": 20,
            "x": 0.68903094,
            "y": 0.85182969
          }
        ]
      }
    },
    {
      "frame_index": 4,
      "timestamp": 0.44444444,
      "hands": {
        "left": [
          {
            "landmark_id": 0,
            "x": 0.30238966,
            "y": 0.57131271
          },
          {
            "landmark_id": 1,
            "x": 0.36085033,
            "y": 0.56253626
          },
          {
            "landmark_id": 2,
            "x": 0.41041119,
            "y": 0.54071659
          },
          {
            "landmark_id": 3,
            "x": 0.44729899,
            "y": 0.52385242
          },
          {
            "landmark_id": 4,
            "x": 0.48054647,
            "y": 0.51321208
          },
          {
            "landmark_id": 5,
            "x": 0.38920546,
            "y": 0.48689243
          },
          {
            "landmark_id": 6,
            "x": 0.42347281,
            "y": 0.45169205
          },
          {
            "landmark_id": 7,
            "x": 0.4459908,
            "y": 0.4312186
          },
          {
            "landmark_id": 8,
            "x": 0.46624205,
            "y": 0.41387619
          },
          {
            "landmark_id": 9,
            "x": 0.3561033,
            "y": 0.47607008
          },
          {
            "landmark_id": 10,
            "x": 0.38636232,
            "y": 0.43380486
          },
          {
            "landmark_id": 11,
            "x": 0.40875591,
            "y": 0.40823106
          },
          {
            "landmark_id": 12,
            "x": 0.42820875,
            "y": 0.38655212
          },
          {
            "landmark_id": 13,
            "x": 0.31916054,
            "y": 0.47506474
          },
          {
            "landmark_id": 14,
            "x": 0.33788065,
            "y": 0.43114084
          },
          {
            "landmark_id": 15,
            "x": 0.35486726,
            "y": 0.40444089
          },
          {
            "landmark_id": 16,
            "x": 0.37304922,
            "y": 0.38212317
          },
          {
            "landmark_id": 17,
            "x": 0.2790771,
            "y": 0.48166605
          },
          {
            "landmark_id": 18,
            "x": 0.28037902,
            "y": 0.44723305
          },
          {
            "landmark_id": 19,
            "x": 0.28591777,
            "y": 0.42463776
          },
          {
            "landmark_id": 20,
            "x": 0.29571277,
            "y": 0.40366594
          }
        ],
        "right": [
          {
            "landmark_id": 0,
            "x": 0.712558,
            "y": 0.53960821
          },
          {
            "landmark_id": 1,
            "x": 0.64768814,
            "y": 0.51449478
          },
          {
            "landmark_id": 2,
            "x": 0.60816491,
            "y": 0.48350976
          },
          {
            "landmark_id": 3,
            "x": 0.58141485,
            "y": 0.46376686
          },
          {
            "landmark_id": 4,
            "x": 0.55638462,
            "y": 0.44893218
          },
          {
            "landmark_id": 5,
            "x": 0.63502679,
            "y": 0.43192031
          },
          {
            "landmark_id": 6,
            "x": 0.58282929,
            "y": 0.40885473
          },
          {
            "landmark_id": 7,
            "x": 0.54747508,
            "y": 0.39856228
          },
          {
            "landmark_id": 8,
            "x": 0.52012615,
            "y": 0.39057444
          },
          {
            "landmark_id": 9,
            "x": 0.6590925,
            "y": 0.43622904
          },
          {
            "landmark_id": 10,
            "x": 0.5906957,
            "y": 0.417078
          },
          {
            "landmark_id": 11,
            "x": 0.55960291,
            "y": 0.4430311
          },
          {
            "landmark_id": 12,
            "x": 0.5537704,
            "y": 0.46645881
          },
          {
            "landmark_id": 13,
            "x": 0.67877341,
            "y": 0.45117635
          },
          {
            "landmark_id": 14,
            "x": 0.60754956,
            "y": 0.4397904
          },
          {
            "landmark_id": 15,
            "x": 0.58889994,
            "y": 0.46952596
          },
          {
            "landmark_id": 16,
            "x": 0.59699577,
            "y": 0.48909285
          },
          {
            "landmark_id": 17,
            "x": 0.6925996,
            "y": 0.47460835
          },
          {
            "landmark_id": 18,
            "x": 0.63346071,
            "y": 0.47506846
          },
          {
            "landmark_id": 19,
            "x": 0.61485274,
            "y": 0.49201106
          },
          {
            "landmark_id": 20,
            "x": 0.62119699,
            "y": 0.50359188
          }
        ]
      }
    },
    {
      "frame_index": 5,
      "timestamp": 0.55555556,
      "hands": {
        "left": [
          {
            "landmark_id": 0,
            "x": 0.29992088,
            "y": 0.57350207
          },
          {
            "landmark_id": 1,
            "x": 0.35802732,
            "y": 0.56458422
          },
          {
            "landmark_id": 2,
            "x": 0.40704181,
            "y": 0.54116006
          },
          {
            "landmark_id": 3,
            "x": 0.44406322,
            "y": 0.52226227
          },
          {
            "landmark_id": 4,
            "x": 0.47806528,
            "y": 0.51141274
          },
          {
            "landmark_id": 5,
            "x": 0.38672229,
            "y": 0.48733909
          },
          {
            "landmark_id": 6,
            "x": 0.42170169,
            "y": 0.45210091
          },
          {
            "landmark_id": 7,
            "x": 0.44456069,
            "y": 0.43081223
          },
          {
            "landmark_id": 8,
            "x": 0.46472404,
            "y": 0.41241731
          },
          {
            "landmark_id": 9,
            "x": 0.35331868,
            "y": 0.47665119
          },
          {
            "landmark_id": 10,
            "x": 0.38300287,
            "y": 0.43383312
          },
          {
            "landmark_id": 11,
            "x": 0.40556475,
            "y": 0.40776969
          },
          {
            "landmark_id": 12,
            "x": 0.42546282,
            "y": 0.38502364
          },
          {
            "landmark_id": 13,
            "x": 0.31661678,
            "y": 0.47591345
          },
          {
            "landmark_id": 14,
            "x": 0.33392567,
            "y": 0.43264138
          },
          {
            "landmark_id": 15,
            "x": 0.35095062,
            "y": 0.40556343
          },
          {
            "landmark_id": 16,
            "x": 0.36947253,
            "y": 0.3824332
          },
          {
            "landmark_id": 17,
            "x": 0.27673751,
            "y": 0.48288613
          },
          {
            "landmark_id": 18,
            "x": 0.27698425,
            "y": 0.44882204
          },
          {
            "landmark_id": 19,
            "x": 0.28240602,
            "y": 0.42639017
          },
          {
            "landmark_id": 20,
            "x": 0.29258953,
            "y": 0.40512769
          }
        ],
        "right": [
          {
            "landmark_id": 0,
            "x": 0.68736188,
            "y": 0.53846421
          },
          {
            "landmark_id": 1,
            "x": 0.61640618,
            "y": 0.5197473
          },
          {
            "landmark_id": 2,
            "x": 0.57342282,
            "y": 0.49341311
          },
          {
            "landmark_id": 3,
            "x": 0.54423599,
            "y": 0.47545489
          },
          {
            "landmark_id": 4,
            "x": 0.5189607,
            "y": 0.464416
          },
          {
            "landmark_id": 5,
            "x": 0.59665521,
            "y": 0.4375826
          },
          {
            "landmark_id": 6,
            "x": 0.5388596,
            "y": 0.41838956
          },
          {
            "landmark_id": 7,
            "x": 0.49828269,
            "y": 0.41185143
          },
          {
            "landmark_id": 8,
            "x": 0.46853389,
            "y": 0.40778438
          },
          {
            "landmark_id": 9,
            "x": 0.61957413,
            "y": 0.44053723
          },
          {
            "landmark_id": 10,
            "x": 0.55019248,
            "y": 0.42320329
          },
          {
            "landmark_id": 11,
            "x": 0.51843147,
            "y": 0.44902045
          },
          {
            "landmark_id": 12,
            "x": 0.5128303,
            "y": 0.47209312
          },
          {
            "landmark_id": 13,
            "x": 0.63770072,
            "y": 0.45450052
          },
          {
            "landmark_id": 14,
            "x": 0.56685311,
            "y": 0.44686009
          },
          {
            "landmark_id": 15,
            "x": 0.55110166,
            "y": 0.47672735
          },
          {
            "landmark_id": 16,
            "x": 0.56137713,
            "y": 0.49658591
          },
          {
            "landmark_id": 17,
            "x": 0.65021688,
            "y": 0.47732661
          },
          {
            "landmark_id": 18,
            "x": 0.58900459,
            "y": 0.48387707
          },
          {
            "landmark_id": 19,
            "x": 0.57473512,
            "y": 0.50238541
          },
          {
            "landmark_id": 20,
            "x": 0.58402979,
            "y": 0.51324495
          }
        ]
      }
    },
    {
      "frame_index": 6,
      "timestamp": 0.66666667,
      "hands": {
        "left": [
          {
            "landmark_id": 0,
            "x": 0.29370276,
            "y": 0.57560606
          },
          {
            "landmark_id": 1,
            "x": 0.35306602,
            "y": 0.56601666
          },
          {
            "landmark_id": 2,
            "x": 0.40190682,
            "y": 0.54153574
          },
          {
            "landmark_id": 3,
            "x": 0.43845702,
            "y": 0.52162972
          },
          {
            "landmark_id": 4,
            "x": 0.47418916,
            "y": 0.50971844
          },
          {
            "landmark_id": 5,
            "x": 0.38340189,
            "y": 0.48803163
          },
          {
            "landmark_id": 6,
            "x": 0.41725435,
            "y": 0.45237873
          },
          {
            "landmark_id": 7,
            "x": 0.4389998,
            "y": 0.4312369
          },
          {
            "landmark_id": 8,
            "x": 0.45823166,
            "y": 0.41284242
          },
          {
            "landmark_id": 9,
            "x": 0.3489573,
            "y": 0.47779243
          },
          {
            "landmark_id": 10,
            "x": 0.37825136,
            "y": 0.43584072
          },
          {
            "landmark_id": 11,
            "x": 0.40015329,
            "y": 0.41004165
          },
          {
            "landmark_id": 12,
            "x": 0.41977744,
            "y": 0.38695444
          },
          {
            "landmark_id": 13,
            "x": 0.31103973,
            "y": 0.47771605
          },
          {
            "landmark_id": 14,
            "x": 0.32885829,
            "y": 0.43505801
          },
          {
            "landmark_id": 15,
            "x": 0.34647089,
            "y": 0.40840903
          },
          {
            "landmark_id": 16,
            "x": 0.36587208,
            "y": 0.38486401
          },
          {
            "landmark_id": 17,
            "x": 0.26994184,
            "y": 0.48535908
          },
          {
            "landmark_id": 18,
            "x": 0.27030161,
            "y": 0.45234772
          },
          {
            "landmark_id": 19,
            "x": 0.275854,
            "y": 0.43041165
          },
          {
            "landmark_id": 20,
            "x": 0.28617254,
            "y": 0.40902727
          }
        ],
        "right": [
          {
            "landmark_id": 0,
            "x": 0.7038248,
            "y": 0.55278656
          },
          {
            "landmark_id": 1,
            "x": 0.63320761,
            "y": 0.5319671
          },
          {
            "landmark_id": 2,
            "x": 0.59041179,
            "y": 0.50387018
          },
          {
            "landmark_id": 3,
            "x": 0.56023685,
            "y": 0.4853307
          },
          {
            "landmark_id": 4,
            "x": 0.53244898,
            "y": 0.47455835
          },
          {
            "landmark_id": 5,
            "x": 0.61507115,
            "y": 0.44724428
          },
          {
            "landmark_id": 6,
            "x": 0.5569753,
            "y": 0.42556706
          },
          {
            "landmark_id": 7,
            "x": 0.51601572,
            "y": 0.41561984
          },
          {
            "landmark_id": 8,
            "x": 0.48366229,
            "y": 0.40964057
          },
          {
            "landmark_id": 9,
            "x": 0.63868569,
            "y": 0.45195714
          },
          {
            "landmark_id": 10,
            "x": 0.56612816,
            "y": 0.43224818
          },
          {
            "landmark_id": 11,
            "x": 0.52768456,
            "y": 0.45429817
          },
          {
            "landmark_id": 12,
            "x": 0.51424084,
            "y": 0.47762703
          },
          {
            "landmark_id": 13,
            "x": 0.65694626,
            "y": 0.46769594
          },
          {
            "landmark_id": 14,
            "x": 0.58219171,
            "y": 0.4596524
          },
          {
            "landmark_id": 15,
            "x": 0.56194489,
            "y": 0.4891283
          },
          {
            "landmark_id": 16,
            "x": 0.56794979,
            "y": 0.51084447
          },
          {
            "landmark_id": 17,
            "x": 0.66821243,
            "y": 0.4924138
          },
          {
            "landmark_id": 18,
            "x": 0.60609632,
            "y": 0.49780169
          },
          {
            "landmark_id": 19,
            "x": 0.59063074,
            "y": 0.51585601
          },
          {
            "landmark_id": 20,
            "x": 0.59842252,
            "y": 0.52753064
          }
        ]
      }
    },
    {
      "frame_index": 7,
      "timestamp": 0.77777778,
      "hands": {
        "left": [
          {
            "landmark_id": 0,
            "x": 0.23936307,
            "y": 0.68858102
          },
          {
            "landmark_id": 1,
            "x": 0.28486261,
            "y": 0.67287212
          },
          {
            "landmark_id": 2,
            "x": 0.33385357,
            "y": 0.63516969
          },
          {
            "landmark_id": 3,
            "x": 0.36937036,
            "y": 0.60608768
          },
          {
            "landmark_id": 4,
            "x": 0.37284059,
            "y": 0.57582846
          },
          {
            "landmark_id": 5,
            "x": 0.28866436,
            "y": 0.56187046
          },
          {
            "landmark_id": 6,
            "x": 0.31174892,
            "y": 0.52849714
          },
          {
            "landmark_id": 7,
            "x": 0.33353573,
            "y": 0.56910385
          },
          {
            "landmark_id": 8,
            "x": 0.3371825,
            "y": 0.59989863
          },
          {
            "landmark_id": 9,
            "x": 0.23989866,
            "y": 0.56393721
          },
          {
            "landmark_id": 10,
            "x": 0.26899512,
            "y": 0.54055263
          },
          {
            "landmark_id": 11,
            "x": 0.29658544,
            "y": 0.58869891
          },
          {
            "landmark_id": 12,
            "x": 0.29715362,
            "y": 0.61616623
          },
          {
            "landmark_id": 13,
            "x": 0.18946951,
            "y": 0.57862634
          },
          {
            "landmark_id": 14,
            "x": 0.20743866,
            "y": 0.5511896
          },
          {
            "landmark_id": 15,
            "x": 0.23613292,
            "y": 0.59140345
          },
          {
            "landmark_id": 16,
            "x": 0.23971661,
            "y": 0.61518844
          },
          {
            "landmark_id": 17,
            "x": 0.14012128,
            "y": 0.60255405
          },
          {
            "landmark_id": 18,
            "x": 0.1370025,
            "y": 0.58226596
          },
          {
            "landmark_id": 19,
            "x": 0.15775929,
            "y": 0.60109452
          },
          {
            "landmark_id": 20,
            "x": 0.1634601,
            "y": 0.6165391
          }
        ],
        "right": [
          {
            "landmark_id": 0,
            "x": 0.77142198,
            "y": 0.87173665
          },
          {
            "landmark_id": 1,
            "x": 0.70558546,
            "y": 0.86298094
          },
          {
            "landmark_id": 2,
            "x": 0.64175895,
            "y": 0.87605583
          },
          {
            "landmark_id": 3,
            "x": 0.59481417,
            "y": 0.89173617
          },
          {
            "landmark_id": 4,
            "x": 0.55891968,
            "y": 0.89942608
          },
          {
            "landmark_id": 5,
            "x": 0.65120383,
            "y": 0.90588533
          },
          {
            "landmark_id": 6,
            "x": 0.59511035,
            "y": 0.95489843
          },
          {
            "landmark_id": 7,
            "x": 0.56849446,
            "y": 0.9858306
          },
          {
            "landmark_id": 8,
            "x": 0.55338056,
            "y": 1.00857258
          },
          {
            "landmark_id": 9,
            "x": 0.68659115,
            "y": 0.92885965
          },
          {
            "landmark_id": 10,
            "x": 0.62678579,
            "y": 0.98565304
          },
          {
            "landmark_id": 11,
            "x": 0.60121544,
            "y": 1.01589973
          },
          {
            "landmark_id": 12,
            "x": 0.58870169,
            "y": 1.03492103
          },
          {
            "landmark_id": 13,
            "x": 0.72502433,
            "y": 0.94801905
          },
          {
            "landmark_id": 14,
            "x": 0.67041514,
            "y": 1.00088662
          },
          {
            "landmark_id": 15,
            "x": 0.64594655,
            "y": 1.02981907
          },
          {
            "landmark_id": 16,
            "x": 0.63532833,
            "y": 1.0476455
          },
          {
            "landmark_id": 17,
            "x": 0.76505713,
            "y": 0.96277986
          },
          {
            "landmark_id": 18,
            "x": 0.7266433,
            "y": 1.00592436
          },
          {
            "landmark_id": 19,
            "x": 0.71038204,
            "y": 1.02817068
          },
          {
            "landmark_id": 20,
            "x": 0.70398415,
            "y": 1.04399096
          }
        ]
      }
    },
    {
      "frame_index": 8,
      "timestamp": 0.88888889,
      "hands": {
        "left": [
          {
            "landmark_id": 0,
            "x": -0.29291189,
            "y": 0.80702865
          },
          {
            "landmark_id": 1,
            "x": -0.18997211,
            "y": 0.78127438
          },
          {
            "landmark_id": 2,
            "x": -0.11412077,
            "y": 0.74626654
          },
          {
            "landmark_id": 3,
            "x": -0.06107306,
            "y": 0.73113483
          },
          {
            "landmark_id": 4,
            "x": -0.02847066,
            "y": 0.74103367
          },
          {
            "landmark_id": 5,
            "x": -0.16175095,
            "y": 0.63728106
          },
          {
            "landmark_id": 6,
            "x": -0.09441673,
            "y": 0.69458061
          },
          {
            "landmark_id": 7,
            "x": -0.07322427,
            "y": 0.75476116
          },
          {
            "landmark_id": 8,
            "x": -0.06944611,
            "y": 0.78991884
          },
          {
            "landmark_id": 9,
            "x": -0.23893086,
            "y": 0.65923572
          },
          {
            "landmark_id": 10,
            "x": -0.14806316,
            "y": 0.74146354
          },
          {
            "landmark_id": 11,
            "x": -0.11948123,
            "y": 0.80322015
          },
          {
            "landmark_id": 12,
            "x": -0.11522358,
            "y": 0.83464104
          },
          {
            "landmark_id": 13,
            "x": -0.302988,
            "y": 0.70226932
          },
          {
            "landmark_id": 14,
            "x": -0.21115793,
            "y": 0.78978002
          },
          {
            "landmark_id": 15,
            "x": -0.17178694,
            "y": 0.84321856
          },
          {
            "landmark_id": 16,
            "x": -0.16216759,
            "y": 0.87004286
          },
          {
            "landmark_id": 17,
            "x": -0.35392141,
            "y": 0.7530573
          },
          {
            "landmark_id": 18,
            "x": -0.27101681,
            "y": 0.8188563
          },
          {
            "landmark_id": 19,
            "x": -0.23529663,
            "y": 0.8577224
          },
          {
            "landmark_id": 20,
            "x": -0.22179503,
            "y": 0.87841213
          }
        ],
        "right": [
          {
            "landmark_id": 0,
            "x": 0.74831774,
            "y": 0.93618142
          },
          {
            "landmark_id": 1,
            "x": 0.69398686,
            "y": 0.91840725
          },
          {
            "landmark_id": 2,
            "x": 0.63253419,
            "y": 0.9207617
          },
          {
            "landmark_id": 3,
            "x": 0.58269209,
            "y": 0.93665454
          },
          {
            "landmark_id": 4,
            "x": 0.54584507,
            "y": 0.95519608
          },
          {
            "landmark_id": 5,
            "x": 0.65727428,
            "y": 0.94752109
          },
          {
            "landmark_id": 6,
            "x": 0.59065845,
            "y": 0.98511218
          },
          {
            "landmark_id": 7,
            "x": 0.56272686,
            "y": 1.00256513
          },
          {
            "landmark_id": 8,
            "x": 0.54916959,
            "y": 1.01224968
          },
          {
            "landmark_id": 9,
            "x": 0.68831403,
            "y": 0.9732511
          },
          {
            "landmark_id": 10,
            "x": 0.62415106,
            "y": 1.01296427
          },
          {
            "landmark_id": 11,
            "x": 0.60418845,
            "y": 1.02526359
          },
          {
            "landmark_id": 12,
            "x": 0.60048323,
            "y": 1.03067201
          },
          {
            "landmark_id": 13,
            "x": 0.71470998,
            "y": 0.99450557
          },
          {
            "landmark_id": 14,
            "x": 0.66209564,
            "y": 1.03168249
          },
          {
            "landmark_id": 15,
            "x": 0.64884624,
            "y": 1.0391468
          },
          {
            "landmark_id": 16,
            "x": 0.64926216,
            "y": 1.03950187
          },
          {
            "landmark_id": 17,
            "x": 0.73501225,
            "y": 1.01068958
          },
          {
            "landmark_id": 18,
            "x": 0.69427853,
            "y": 1.04105347
          },
          {
            "landmark_id": 19,
            "x": 0.68358849,
            "y": 1.0479633
          },
          {
            "landmark_id": 20,
            "x": 0.68362497,
            "y": 1.04992005
          }
        ]
      }
    },
    {
      "frame_index": 9,
      "timestamp": 1.0,
      "hands": {
        "left": [
          {
            "landmark_id": 0,
            "x": -0.86513411,
            "y": 0.80702865
          },
          {
            "landmark_id": 1,
            "x": -0.76219433,
            "y": 0.78127438
          },
          {
            "landmark_id": 2,
            "x": -0.686343,
            "y": 0.74626654
          },
          {
            "landmark_id": 3,
            "x": -0.63329528,
            "y": 0.73113483
          },
          {
            "landmark_id": 4,
            "x": -0.60069288,
            "y": 0.74103367
          },
          {
            "landmark_id": 5,
            "x": -0.73397317,
            "y": 0.63728106
          },
          {
            "landmark_id": 6,
            "x": -0.66663895,
            "y": 0.69458061
          },
          {
            "landmark_id": 7,
            "x": -0.64544649,
            "y": 0.75476116
          },
          {
            "landmark_id": 8,
            "x": -0.64166833,
            "y": 0.78991884
          },
          {
            "landmark_id": 9,
            "x": -0.81115308,
            "y": 0.65923572
          },
          {
            "landmark_id": 10,
            "x": -0.72028538,
            "y": 0.74146354
          },
          {
            "landmark_id": 11,
            "x": -0.69170345,
            "y": 0.80322015
          },
          {
            "landmark_id": 12,
            "x": -0.6874458,
            "y": 0.83464104
          },
          {
            "landmark_id": 13,
            "x": -0.87521022,
            "y": 0.70226932
          },
          {
            "landmark_id": 14,
            "x": -0.78338015,
            "y": 0.78978002
          },
          {
            "landmark_id": 15,
            "x": -0.74400916,
            "y": 0.84321856
          },
          {
            "landmark_id": 16,
            "x": -0.73438981,
            "y": 0.87004286
          },
          {
            "landmark_id": 17,
            "x": -0.92614363,
            "y": 0.7530573
          },
          {
            "landmark_id": 18,
            "x": -0.84323904,
            "y": 0.8188563
          },
          {
            "landmark_id": 19,
            "x": -0.80751885,
            "y": 0.8577224
          },
          {
            "landmark_id": 20,
            "x": -0.79401725,
            "y": 0.87841213
          }
        ],
        "right": [
          {
            "landmark_id": 0,
            "x": 0.76574624,
            "y": 0.95186692
          },
          {
            "landmark_id": 1,
            "x": 0.71387076,
            "y": 0.92713112
          },
          {
            "landmark_id": 2,
            "x": 0.65401858,
            "y": 0.92275679
          },
          {
            "landmark_id": 3,
            "x": 0.60350555,
            "y": 0.93620241
          },
          {
            "landmark_id": 4,
            "x": 0.56519723,
            "y": 0.95291066
          },
          {
            "landmark_id": 5,
            "x": 0.68268752,
            "y": 0.95732045
          },
          {
            "landmark_id": 6,
            "x": 0.60581744,
            "y": 0.99153143
          },
          {
            "landmark_id": 7,
            "x": 0.59229112,
            "y": 0.99959552
          },
          {
            "landmark_id": 8,
            "x": 0.59329772,
            "y": 1.00391781
          },
          {
            "landmark_id": 9,
            "x": 0.71055162,
            "y": 0.98586529
          },
          {
            "landmark_id": 10,
            "x": 0.63774818,
            "y": 1.02023387
          },
          {
            "landmark_id": 11,
            "x": 0.62309015,
            "y": 1.02629721
          },
          {
            "landmark_id": 12,
            "x": 0.62351173,
            "y": 1.02788687
          },
          {
            "landmark_id": 13,
            "x": 0.72987103,
            "y": 1.00858903
          },
          {
            "landmark_id": 14,
            "x": 0.66770613,
            "y": 1.03986526
          },
          {
            "landmark_id": 15,
            "x": 0.65889442,
            "y": 1.04198587
          },
          {
            "landmark_id": 16,
            "x": 0.66427606,
            "y": 1.04040599
          },
          {
            "landmark_id": 17,
            "x": 0.73984152,
            "y": 1.02575874
          },
          {
            "landmark_id": 18,
            "x": 0.69214076,
            "y": 1.05092454
          },
          {
            "landmark_id": 19,
            "x": 0.68580711,
            "y": 1.05352509
          },
          {
            "landmark_id": 20,
            "x": 0.69115305,
            "y": 1.05414534
          }
        ]
      }
    }
  ]
}